{
  "name": "GroceryList",
  "plural": "grocery",
  "base": "PersistedModel",
  "idInjection": true,
  "options": {
    "validateUpsert": true
  },
  "properties": {

    "departments": {
      "type": [
        "object"
      ],
      "required": true
    },

    "img": {
      "type": "string",
      "required": true
    },

    "desc": {
      "type": "string",
      "required": true
    },

    "slug": {
      "type": "string",
      "required": true
    },

    "created_at": {
      "type": "date"
    },

    "updated_at": {
      "type": "date"
    }

  },
  "validations" : [],
  "relations"   : {},
  "acls"        : [],
  "methods"     : {}
}
