{
  "name"  : "recipe",
  "plural": "recipe",
  "base"  : "Model",
  "idInjection": true,
  "options": {
    "validateUpsert": true
  },
  "properties": {

    "id": {
      "type": "string",
      "required": true
    },

    "name": {
      "type": "string",
      "required": true
    },

    "img": {
      "type": "string",
      "required": true
    },

    "url": {
      "type": "string"
    },

    "title": {
      "type": "string",
      "required": true
    },

    "ingredients": {
      "type": [
        "object"
      ],
      "required": true
    },

    "directions": {
      "type": [
        "object"
      ],
      "required": true
    },    
    "prepTime":{
      "type": "string",
          "required": true
    },
    "totalTime":{
      "type": "string",
          "required": true
    },
    "recipeYield":{
      "type": "string",
          "required": true
    },
        "createdAt": {
      "type": "date"
    },
    "lastModifiedAt": {
      "type": "date"
    }    

  },
  "validations": [],
  "relations"  : {},
  "acls"       : [],
  "methods"    : {}
}
